[{"r":63,"g":15,"b":158,"label":"blue-ish"},{"r":225,"g":212,"b":241,"label":"blue-ish"},{"r":33,"g":179,"b":107,"label":"green-ish"},{"r":64,"g":108,"b":69,"label":"green-ish"},{"r":73,"g":214,"b":68,"label":"green-ish"},{"r":23,"g":37,"b":251,"label":"blue-ish"},{"r":3,"g":178,"b":0,"label":"green-ish"},{"r":98,"g":137,"b":81,"label":"green-ish"},{"r":62,"g":152,"b":139,"label":"green-ish"},{"r":5,"g":89,"b":185,"label":"blue-ish"},{"r":170,"g":223,"b":198,"label":"green-ish"},{"r":100,"g":66,"b":6,"label":"red-ish"},{"r":132,"g":180,"b":156,"label":"green-ish"},{"r":66,"g":186,"b":83,"label":"green-ish"},{"r":5,"g":159,"b":30,"label":"green-ish"},{"r":99,"g":186,"b":208,"label":"blue-ish"},{"r":165,"g":120,"b":202,"label":"blue-ish"},{"r":137,"g":145,"b":74,"label":"green-ish"},{"r":207,"g":200,"b":217,"label":"blue-ish"},{"r":31,"g":163,"b":80,"label":"green-ish"},{"r":7,"g":96,"b":154,"label":"blue-ish"},{"r":64,"g":148,"b":195,"label":"blue-ish"},{"r":189,"g":78,"b":137,"label":"red-ish"},{"r":244,"g":84,"b":184,"label":"red-ish"},{"r":88,"g":11,"b":138,"label":"blue-ish"},{"r":66,"g":187,"b":183,"label":"green-ish"},{"r":95,"g":224,"b":129,"label":"green-ish"},{"r":144,"g":160,"b":183,"label":"blue-ish"},{"r":76,"g":210,"b":45,"label":"green-ish"},{"r":182,"g":126,"b":95,"label":"red-ish"},{"r":39,"g":68,"b":106,"label":"blue-ish"},{"r":12,"g":196,"b":181,"label":"green-ish"},{"r":201,"g":26,"b":59,"label":"red-ish"},{"r":209,"g":195,"b":241,"label":"blue-ish"},{"r":81,"g":137,"b":202,"label":"blue-ish"},{"r":14,"g":157,"b":13,"label":"green-ish"},{"r":35,"g":147,"b":62,"label":"green-ish"},{"r":142,"g":202,"b":70,"label":"green-ish"},{"r":173,"g":122,"b":16,"label":"red-ish"},{"r":68,"g":171,"b":53,"label":"green-ish"},{"r":22,"g":250,"b":50,"label":"green-ish"},{"r":181,"g":83,"b":47,"label":"red-ish"},{"r":189,"g":193,"b":254,"label":"blue-ish"},{"r":167,"g":254,"b":176,"label":"green-ish"},{"r":82,"g":188,"b":167,"label":"green-ish"},{"r":62,"g":100,"b":240,"label":"blue-ish"},{"r":116,"g":229,"b":83,"label":"green-ish"},{"r":19,"g":231,"b":31,"label":"green-ish"},{"r":249,"g":232,"b":242,"label":"red-ish"},{"r":223,"g":150,"b":123,"label":"red-ish"},{"r":97,"g":78,"b":26,"label":"red-ish"},{"r":210,"g":0,"b":26,"label":"red-ish"},{"r":4,"g":67,"b":84,"label":"blue-ish"},{"r":225,"g":52,"b":251,"label":"blue-ish"},{"r":230,"g":114,"b":229,"label":"red-ish"},{"r":2,"g":180,"b":26,"label":"green-ish"},{"r":71,"g":151,"b":160,"label":"blue-ish"},{"r":196,"g":104,"b":189,"label":"red-ish"},{"r":183,"g":44,"b":127,"label":"red-ish"},{"r":134,"g":131,"b":158,"label":"blue-ish"},{"r":225,"g":215,"b":198,"label":"red-ish"},{"r":3,"g":130,"b":118,"label":"green-ish"},{"r":123,"g":230,"b":91,"label":"green-ish"},{"r":14,"g":157,"b":242,"label":"blue-ish"},{"r":15,"g":129,"b":84,"label":"green-ish"},{"r":106,"g":119,"b":230,"label":"blue-ish"},{"r":201,"g":131,"b":195,"label":"red-ish"},{"r":149,"g":251,"b":195,"label":"green-ish"},{"r":174,"g":34,"b":57,"label":"red-ish"},{"r":210,"g":193,"b":111,"label":"red-ish"},{"r":117,"g":71,"b":158,"label":"blue-ish"},{"r":90,"g":167,"b":68,"label":"green-ish"},{"r":151,"g":65,"b":215,"label":"blue-ish"},{"r":95,"g":140,"b":46,"label":"green-ish"},{"r":105,"g":4,"b":247,"label":"blue-ish"},{"r":125,"g":99,"b":61,"label":"red-ish"},{"r":239,"g":174,"b":30,"label":"red-ish"},{"r":67,"g":156,"b":152,"label":"green-ish"},{"r":219,"g":245,"b":123,"label":"green-ish"},{"r":90,"g":89,"b":222,"label":"blue-ish"},{"r":78,"g":131,"b":11,"label":"green-ish"},{"r":96,"g":176,"b":246,"label":"blue-ish"},{"r":120,"g":47,"b":10,"label":"red-ish"},{"r":13,"g":35,"b":78,"label":"blue-ish"},{"r":92,"g":17,"b":108,"label":"blue-ish"},{"r":162,"g":13,"b":125,"label":"red-ish"},{"r":221,"g":35,"b":252,"label":"blue-ish"},{"r":90,"g":19,"b":174,"label":"blue-ish"},{"r":145,"g":190,"b":196,"label":"blue-ish"},{"r":31,"g":217,"b":183,"label":"green-ish"},{"r":240,"g":57,"b":222,"label":"red-ish"},{"r":30,"g":36,"b":197,"label":"blue-ish"},{"r":214,"g":134,"b":53,"label":"red-ish"},{"r":18,"g":95,"b":199,"label":"blue-ish"},{"r":146,"g":245,"b":177,"label":"green-ish"},{"r":50,"g":99,"b":102,"label":"blue-ish"},{"r":197,"g":115,"b":52,"label":"red-ish"},{"r":115,"g":244,"b":3,"label":"green-ish"},{"r":10,"g":181,"b":78,"label":"green-ish"},{"r":9,"g":121,"b":220,"label":"blue-ish"},{"r":152,"g":14,"b":64,"label":"red-ish"},{"r":69,"g":222,"b":3,"label":"green-ish"},{"r":243,"g":14,"b":157,"label":"red-ish"},{"r":232,"g":11,"b":19,"label":"red-ish"},{"r":249,"g":62,"b":144,"label":"red-ish"},{"r":82,"g":49,"b":41,"label":"red-ish"},{"r":248,"g":187,"b":84,"label":"red-ish"},{"r":227,"g":125,"b":126,"label":"red-ish"},{"r":216,"g":155,"b":72,"label":"red-ish"},{"r":182,"g":240,"b":139,"label":"green-ish"},{"r":147,"g":38,"b":191,"label":"blue-ish"},{"r":214,"g":207,"b":148,"label":"red-ish"},{"r":167,"g":181,"b":157,"label":"green-ish"},{"r":226,"g":187,"b":22,"label":"red-ish"},{"r":244,"g":56,"b":213,"label":"red-ish"},{"r":93,"g":234,"b":107,"label":"green-ish"},{"r":114,"g":107,"b":162,"label":"blue-ish"},{"r":163,"g":147,"b":227,"label":"blue-ish"},{"r":208,"g":22,"b":172,"label":"red-ish"},{"r":142,"g":39,"b":34,"label":"red-ish"},{"r":206,"g":62,"b":165,"label":"red-ish"},{"r":16,"g":151,"b":6,"label":"green-ish"},{"r":198,"g":89,"b":112,"label":"red-ish"},{"r":89,"g":155,"b":196,"label":"blue-ish"},{"r":121,"g":184,"b":186,"label":"blue-ish"},{"r":165,"g":191,"b":95,"label":"green-ish"},{"r":248,"g":125,"b":183,"label":"red-ish"},{"r":175,"g":241,"b":192,"label":"green-ish"},{"r":231,"g":143,"b":103,"label":"red-ish"},{"r":169,"g":5,"b":47,"label":"red-ish"},{"r":90,"g":69,"b":211,"label":"blue-ish"},{"r":105,"g":144,"b":210,"label":"blue-ish"},{"r":77,"g":82,"b":236,"label":"blue-ish"},{"r":121,"g":254,"b":55,"label":"green-ish"},{"r":173,"g":251,"b":188,"label":"green-ish"},{"r":1,"g":58,"b":204,"label":"blue-ish"},{"r":37,"g":145,"b":95,"label":"green-ish"},{"r":144,"g":86,"b":151,"label":"blue-ish"},{"r":132,"g":180,"b":171,"label":"green-ish"},{"r":52,"g":209,"b":3,"label":"green-ish"},{"r":43,"g":225,"b":185,"label":"green-ish"},{"r":87,"g":216,"b":124,"label":"green-ish"},{"r":133,"g":207,"b":206,"label":"green-ish"},{"r":128,"g":210,"b":201,"label":"green-ish"},{"r":160,"g":227,"b":196,"label":"green-ish"},{"r":43,"g":152,"b":9,"label":"green-ish"},{"r":212,"g":99,"b":177,"label":"red-ish"},{"r":242,"g":63,"b":130,"label":"red-ish"},{"r":101,"g":204,"b":250,"label":"blue-ish"},{"r":215,"g":48,"b":113,"label":"red-ish"},{"r":12,"g":115,"b":126,"label":"blue-ish"},{"r":51,"g":51,"b":158,"label":"blue-ish"},{"r":208,"g":153,"b":141,"label":"red-ish"},{"r":130,"g":32,"b":109,"label":"red-ish"},{"r":126,"g":167,"b":48,"label":"green-ish"},{"r":43,"g":126,"b":223,"label":"blue-ish"},{"r":145,"g":245,"b":159,"label":"green-ish"},{"r":91,"g":155,"b":178,"label":"blue-ish"},{"r":56,"g":88,"b":96,"label":"blue-ish"},{"r":90,"g":160,"b":68,"label":"green-ish"},{"r":35,"g":134,"b":35,"label":"green-ish"},{"r":9,"g":236,"b":3,"label":"green-ish"},{"r":162,"g":247,"b":91,"label":"green-ish"},{"r":30,"g":83,"b":249,"label":"blue-ish"},{"r":147,"g":5,"b":65,"label":"red-ish"},{"r":41,"g":38,"b":97,"label":"blue-ish"},{"r":182,"g":238,"b":222,"label":"green-ish"},{"r":9,"g":164,"b":34,"label":"green-ish"},{"r":148,"g":163,"b":167,"label":"blue-ish"},{"r":234,"g":40,"b":200,"label":"red-ish"},{"r":67,"g":22,"b":153,"label":"blue-ish"},{"r":149,"g":144,"b":155,"label":"blue-ish"},{"r":87,"g":130,"b":202,"label":"blue-ish"},{"r":234,"g":107,"b":136,"label":"red-ish"},{"r":156,"g":74,"b":140,"label":"red-ish"},{"r":179,"g":215,"b":56,"label":"green-ish"},{"r":23,"g":204,"b":109,"label":"green-ish"},{"r":223,"g":158,"b":112,"label":"red-ish"},{"r":72,"g":142,"b":220,"label":"blue-ish"},{"r":151,"g":164,"b":70,"label":"green-ish"},{"r":53,"g":47,"b":86,"label":"blue-ish"},{"r":179,"g":124,"b":29,"label":"red-ish"},{"r":154,"g":134,"b":37,"label":"red-ish"},{"r":92,"g":152,"b":232,"label":"blue-ish"},{"r":60,"g":169,"b":10,"label":"green-ish"},{"r":136,"g":5,"b":36,"label":"red-ish"},{"r":163,"g":23,"b":8,"label":"red-ish"},{"r":98,"g":152,"b":198,"label":"blue-ish"},{"r":57,"g":112,"b":44,"label":"green-ish"},{"r":250,"g":138,"b":117,"label":"red-ish"},{"r":217,"g":141,"b":7,"label":"red-ish"},{"r":50,"g":197,"b":246,"label":"blue-ish"},{"r":85,"g":5,"b":143,"label":"blue-ish"},{"r":92,"g":81,"b":178,"label":"blue-ish"},{"r":221,"g":57,"b":38,"label":"red-ish"},{"r":24,"g":229,"b":83,"label":"green-ish"},{"r":106,"g":95,"b":68,"label":"red-ish"},{"r":204,"g":16,"b":254,"label":"blue-ish"},{"r":13,"g":73,"b":225,"label":"blue-ish"},{"r":142,"g":81,"b":182,"label":"blue-ish"},{"r":57,"g":167,"b":242,"label":"blue-ish"},{"r":146,"g":252,"b":167,"label":"green-ish"},{"r":205,"g":126,"b":165,"label":"red-ish"},{"r":72,"g":78,"b":129,"label":"blue-ish"},{"r":58,"g":45,"b":101,"label":"blue-ish"},{"r":240,"g":222,"b":97,"label":"red-ish"},{"r":54,"g":186,"b":136,"label":"green-ish"},{"r":155,"g":180,"b":169,"label":"green-ish"},{"r":24,"g":173,"b":190,"label":"blue-ish"},{"r":163,"g":73,"b":190,"label":"blue-ish"},{"r":84,"g":111,"b":67,"label":"green-ish"},{"r":99,"g":127,"b":22,"label":"green-ish"},{"r":87,"g":243,"b":87,"label":"green-ish"},{"r":185,"g":12,"b":32,"label":"red-ish"},{"r":146,"g":186,"b":129,"label":"green-ish"},{"r":9,"g":208,"b":76,"label":"green-ish"},{"r":225,"g":148,"b":114,"label":"red-ish"},{"r":82,"g":24,"b":225,"label":"blue-ish"},{"r":162,"g":1,"b":58,"label":"red-ish"},{"r":52,"g":57,"b":88,"label":"blue-ish"},{"r":17,"g":202,"b":143,"label":"green-ish"},{"r":100,"g":43,"b":243,"label":"blue-ish"},{"r":137,"g":178,"b":172,"label":"green-ish"},{"r":193,"g":119,"b":226,"label":"blue-ish"},{"r":36,"g":225,"b":177,"label":"green-ish"},{"r":46,"g":113,"b":200,"label":"blue-ish"},{"r":202,"g":50,"b":115,"label":"red-ish"},{"r":180,"g":151,"b":160,"label":"red-ish"},{"r":58,"g":62,"b":111,"label":"blue-ish"},{"r":29,"g":215,"b":11,"label":"green-ish"},{"r":161,"g":228,"b":68,"label":"green-ish"},{"r":223,"g":212,"b":204,"label":"red-ish"},{"r":192,"g":13,"b":150,"label":"red-ish"},{"r":204,"g":141,"b":154,"label":"red-ish"},{"r":243,"g":146,"b":0,"label":"red-ish"},{"r":186,"g":249,"b":194,"label":"green-ish"},{"r":169,"g":41,"b":192,"label":"blue-ish"},{"r":144,"g":82,"b":40,"label":"red-ish"},{"r":129,"g":223,"b":10,"label":"green-ish"},{"r":15,"g":193,"b":85,"label":"green-ish"},{"r":49,"g":42,"b":72,"label":"blue-ish"},{"r":38,"g":189,"b":65,"label":"green-ish"},{"r":56,"g":109,"b":79,"label":"green-ish"},{"r":22,"g":182,"b":63,"label":"green-ish"},{"r":173,"g":242,"b":107,"label":"green-ish"},{"r":179,"g":31,"b":129,"label":"red-ish"},{"r":116,"g":189,"b":123,"label":"green-ish"},{"r":238,"g":84,"b":21,"label":"red-ish"},{"r":27,"g":135,"b":48,"label":"green-ish"},{"r":78,"g":201,"b":59,"label":"green-ish"},{"r":77,"g":177,"b":108,"label":"green-ish"},{"r":70,"g":160,"b":168,"label":"blue-ish"},{"r":97,"g":181,"b":12,"label":"green-ish"},{"r":214,"g":40,"b":249,"label":"blue-ish"},{"r":152,"g":194,"b":113,"label":"green-ish"},{"r":44,"g":140,"b":136,"label":"green-ish"},{"r":181,"g":236,"b":23,"label":"green-ish"},{"r":87,"g":15,"b":42,"label":"red-ish"},{"r":176,"g":66,"b":185,"label":"blue-ish"},{"r":102,"g":53,"b":160,"label":"blue-ish"},{"r":133,"g":106,"b":36,"label":"red-ish"},{"r":195,"g":244,"b":185,"label":"green-ish"},{"r":55,"g":163,"b":37,"label":"green-ish"},{"r":104,"g":101,"b":112,"label":"blue-ish"},{"r":185,"g":243,"b":248,"label":"blue-ish"},{"r":70,"g":113,"b":253,"label":"blue-ish"},{"r":84,"g":165,"b":18,"label":"green-ish"},{"r":61,"g":83,"b":61,"label":"green-ish"},{"r":191,"g":100,"b":125,"label":"red-ish"},{"r":152,"g":116,"b":239,"label":"blue-ish"},{"r":106,"g":251,"b":31,"label":"green-ish"},{"r":80,"g":161,"b":62,"label":"green-ish"},{"r":39,"g":241,"b":106,"label":"green-ish"},{"r":203,"g":246,"b":204,"label":"green-ish"},{"r":204,"g":187,"b":29,"label":"red-ish"},{"r":239,"g":197,"b":57,"label":"red-ish"},{"r":182,"g":73,"b":187,"label":"blue-ish"},{"r":142,"g":31,"b":179,"label":"blue-ish"},{"r":190,"g":203,"b":232,"label":"blue-ish"},{"r":136,"g":75,"b":249,"label":"blue-ish"},{"r":164,"g":251,"b":94,"label":"green-ish"},{"r":190,"g":247,"b":253,"label":"blue-ish"},{"r":98,"g":11,"b":113,"label":"blue-ish"},{"r":133,"g":250,"b":23,"label":"green-ish"},{"r":168,"g":156,"b":117,"label":"red-ish"},{"r":182,"g":231,"b":229,"label":"green-ish"},{"r":71,"g":254,"b":248,"label":"green-ish"},{"r":92,"g":92,"b":78,"label":"red-ish"},{"r":79,"g":148,"b":134,"label":"green-ish"},{"r":217,"g":221,"b":97,"label":"green-ish"},{"r":66,"g":28,"b":111,"label":"blue-ish"},{"r":101,"g":252,"b":142,"label":"green-ish"},{"r":216,"g":209,"b":30,"label":"red-ish"},{"r":25,"g":5,"b":41,"label":"blue-ish"},{"r":78,"g":244,"b":187,"label":"green-ish"},{"r":88,"g":8,"b":40,"label":"red-ish"},{"r":74,"g":244,"b":225,"label":"green-ish"},{"r":172,"g":28,"b":60,"label":"red-ish"},{"r":90,"g":236,"b":173,"label":"green-ish"},{"r":38,"g":130,"b":59,"label":"green-ish"},{"r":154,"g":137,"b":239,"label":"blue-ish"},{"r":110,"g":36,"b":65,"label":"red-ish"},{"r":47,"g":236,"b":196,"label":"green-ish"},{"r":68,"g":224,"b":145,"label":"green-ish"},{"r":35,"g":205,"b":182,"label":"green-ish"},{"r":238,"g":37,"b":92,"label":"red-ish"},{"r":143,"g":171,"b":172,"label":"blue-ish"},{"r":247,"g":96,"b":238,"label":"red-ish"},{"r":142,"g":79,"b":107,"label":"red-ish"},{"r":137,"g":16,"b":253,"label":"blue-ish"},{"r":166,"g":204,"b":217,"label":"blue-ish"},{"r":118,"g":193,"b":146,"label":"green-ish"},{"r":216,"g":71,"b":244,"label":"blue-ish"},{"r":112,"g":176,"b":35,"label":"green-ish"},{"r":86,"g":36,"b":199,"label":"blue-ish"},{"r":190,"g":230,"b":140,"label":"green-ish"},{"r":219,"g":134,"b":169,"label":"red-ish"},{"r":253,"g":131,"b":90,"label":"red-ish"},{"r":206,"g":49,"b":253,"label":"blue-ish"},{"r":212,"g":234,"b":176,"label":"green-ish"},{"r":114,"g":167,"b":126,"label":"green-ish"},{"r":89,"g":233,"b":71,"label":"green-ish"},{"r":204,"g":234,"b":48,"label":"green-ish"},{"r":171,"g":112,"b":173,"label":"blue-ish"},{"r":65,"g":19,"b":156,"label":"blue-ish"},{"r":89,"g":101,"b":167,"label":"blue-ish"},{"r":6,"g":236,"b":111,"label":"green-ish"},{"r":248,"g":7,"b":250,"label":"blue-ish"},{"r":149,"g":220,"b":115,"label":"green-ish"},{"r":23,"g":48,"b":112,"label":"blue-ish"},{"r":204,"g":178,"b":43,"label":"red-ish"},{"r":207,"g":96,"b":99,"label":"red-ish"},{"r":199,"g":47,"b":114,"label":"red-ish"},{"r":115,"g":36,"b":74,"label":"red-ish"},{"r":155,"g":6,"b":15,"label":"red-ish"},{"r":171,"g":33,"b":229,"label":"blue-ish"},{"r":96,"g":103,"b":181,"label":"blue-ish"},{"r":187,"g":162,"b":164,"label":"red-ish"},{"r":194,"g":51,"b":166,"label":"red-ish"},{"r":62,"g":38,"b":58,"label":"red-ish"},{"r":174,"g":173,"b":230,"label":"blue-ish"},{"r":187,"g":69,"b":205,"label":"blue-ish"},{"r":63,"g":134,"b":177,"label":"blue-ish"},{"r":177,"g":12,"b":23,"label":"red-ish"},{"r":162,"g":121,"b":167,"label":"blue-ish"},{"r":223,"g":232,"b":148,"label":"green-ish"},{"r":94,"g":151,"b":119,"label":"green-ish"},{"r":159,"g":223,"b":60,"label":"green-ish"},{"r":40,"g":103,"b":101,"label":"green-ish"},{"r":194,"g":197,"b":150,"label":"green-ish"},{"r":130,"g":28,"b":214,"label":"blue-ish"},{"r":88,"g":57,"b":117,"label":"blue-ish"},{"r":19,"g":175,"b":44,"label":"green-ish"},{"r":20,"g":136,"b":37,"label":"green-ish"},{"r":143,"g":13,"b":91,"label":"red-ish"},{"r":114,"g":101,"b":133,"label":"blue-ish"},{"r":46,"g":157,"b":169,"label":"blue-ish"},{"r":86,"g":137,"b":197,"label":"blue-ish"},{"r":156,"g":220,"b":153,"label":"green-ish"},{"r":104,"g":229,"b":253,"label":"blue-ish"},{"r":183,"g":143,"b":15,"label":"red-ish"},{"r":245,"g":219,"b":168,"label":"red-ish"},{"r":103,"g":61,"b":203,"label":"blue-ish"},{"r":73,"g":166,"b":211,"label":"blue-ish"},{"r":228,"g":8,"b":237,"label":"blue-ish"},{"r":237,"g":247,"b":62,"label":"green-ish"},{"r":91,"g":21,"b":210,"label":"blue-ish"},{"r":78,"g":4,"b":17,"label":"red-ish"},{"r":239,"g":100,"b":124,"label":"red-ish"},{"r":156,"g":156,"b":230,"label":"blue-ish"},{"r":79,"g":232,"b":227,"label":"green-ish"},{"r":222,"g":143,"b":140,"label":"red-ish"},{"r":170,"g":91,"b":93,"label":"red-ish"},{"r":97,"g":215,"b":61,"label":"green-ish"},{"r":207,"g":58,"b":15,"label":"red-ish"},{"r":157,"g":199,"b":197,"label":"green-ish"},{"r":12,"g":12,"b":35,"label":"blue-ish"},{"r":213,"g":12,"b":136,"label":"red-ish"},{"r":90,"g":98,"b":4,"label":"green-ish"},{"r":31,"g":43,"b":88,"label":"blue-ish"},{"r":163,"g":106,"b":100,"label":"red-ish"},{"r":63,"g":83,"b":1,"label":"green-ish"},{"r":225,"g":79,"b":196,"label":"red-ish"},{"r":196,"g":80,"b":110,"label":"red-ish"},{"r":117,"g":124,"b":184,"label":"blue-ish"},{"r":205,"g":180,"b":172,"label":"red-ish"},{"r":53,"g":86,"b":228,"label":"blue-ish"},{"r":60,"g":155,"b":159,"label":"blue-ish"},{"r":119,"g":23,"b":57,"label":"red-ish"},{"r":164,"g":96,"b":138,"label":"red-ish"},{"r":191,"g":171,"b":124,"label":"red-ish"},{"r":160,"g":79,"b":138,"label":"red-ish"},{"r":41,"g":221,"b":115,"label":"green-ish"},{"r":115,"g":109,"b":215,"label":"blue-ish"},{"r":157,"g":95,"b":127,"label":"red-ish"},{"r":208,"g":74,"b":67,"label":"red-ish"},{"r":130,"g":57,"b":22,"label":"red-ish"},{"r":41,"g":78,"b":9,"label":"green-ish"},{"r":173,"g":110,"b":89,"label":"red-ish"},{"r":98,"g":162,"b":131,"label":"green-ish"},{"r":143,"g":87,"b":250,"label":"blue-ish"},{"r":179,"g":216,"b":72,"label":"green-ish"},{"r":46,"g":148,"b":203,"label":"blue-ish"},{"r":200,"g":27,"b":37,"label":"red-ish"},{"r":80,"g":235,"b":7,"label":"green-ish"},{"r":164,"g":211,"b":23,"label":"green-ish"},{"r":172,"g":204,"b":218,"label":"blue-ish"},{"r":195,"g":171,"b":116,"label":"red-ish"},{"r":174,"g":175,"b":23,"label":"green-ish"},{"r":17,"g":245,"b":87,"label":"green-ish"},{"r":128,"g":218,"b":122,"label":"green-ish"},{"r":68,"g":34,"b":195,"label":"blue-ish"},{"r":120,"g":45,"b":46,"label":"red-ish"},{"r":192,"g":70,"b":181,"label":"red-ish"},{"r":167,"g":64,"b":122,"label":"red-ish"},{"r":10,"g":104,"b":253,"label":"blue-ish"},{"r":186,"g":166,"b":150,"label":"red-ish"},{"r":185,"g":32,"b":128,"label":"red-ish"},{"r":115,"g":125,"b":213,"label":"blue-ish"},{"r":95,"g":179,"b":244,"label":"blue-ish"},{"r":49,"g":75,"b":159,"label":"blue-ish"},{"r":169,"g":22,"b":211,"label":"blue-ish"},{"r":141,"g":159,"b":85,"label":"green-ish"},{"r":42,"g":251,"b":223,"label":"green-ish"},{"r":249,"g":176,"b":101,"label":"red-ish"},{"r":155,"g":234,"b":36,"label":"green-ish"},{"r":33,"g":166,"b":160,"label":"green-ish"},{"r":95,"g":219,"b":11,"label":"green-ish"},{"r":220,"g":191,"b":20,"label":"red-ish"},{"r":140,"g":24,"b":217,"label":"blue-ish"},{"r":230,"g":83,"b":37,"label":"red-ish"},{"r":139,"g":142,"b":156,"label":"blue-ish"},{"r":199,"g":45,"b":184,"label":"red-ish"},{"r":68,"g":134,"b":3,"label":"green-ish"},{"r":201,"g":55,"b":55,"label":"red-ish"},{"r":58,"g":48,"b":98,"label":"blue-ish"},{"r":133,"g":156,"b":62,"label":"green-ish"},{"r":10,"g":230,"b":237,"label":"blue-ish"},{"r":3,"g":10,"b":155,"label":"blue-ish"},{"r":254,"g":50,"b":197,"label":"red-ish"},{"r":108,"g":148,"b":107,"label":"green-ish"},{"r":45,"g":139,"b":239,"label":"blue-ish"},{"r":93,"g":253,"b":140,"label":"green-ish"},{"r":230,"g":123,"b":213,"label":"red-ish"},{"r":73,"g":110,"b":167,"label":"blue-ish"},{"r":225,"g":156,"b":80,"label":"red-ish"},{"r":198,"g":189,"b":160,"label":"red-ish"},{"r":6,"g":8,"b":214,"label":"blue-ish"},{"r":77,"g":41,"b":175,"label":"blue-ish"},{"r":123,"g":15,"b":42,"label":"red-ish"},{"r":164,"g":170,"b":4,"label":"green-ish"},{"r":64,"g":124,"b":245,"label":"blue-ish"},{"r":31,"g":8,"b":131,"label":"blue-ish"},{"r":84,"g":203,"b":15,"label":"green-ish"},{"r":82,"g":29,"b":185,"label":"blue-ish"},{"r":113,"g":155,"b":37,"label":"green-ish"},{"r":238,"g":94,"b":225,"label":"red-ish"},{"r":249,"g":68,"b":147,"label":"red-ish"},{"r":154,"g":245,"b":185,"label":"green-ish"},{"r":60,"g":183,"b":59,"label":"green-ish"},{"r":121,"g":184,"b":41,"label":"green-ish"},{"r":224,"g":123,"b":210,"label":"red-ish"},{"r":27,"g":194,"b":216,"label":"blue-ish"},{"r":102,"g":30,"b":86,"label":"red-ish"},{"r":173,"g":252,"b":118,"label":"green-ish"},{"r":0,"g":192,"b":198,"label":"blue-ish"},{"r":95,"g":157,"b":54,"label":"green-ish"},{"r":139,"g":178,"b":186,"label":"blue-ish"},{"r":131,"g":68,"b":198,"label":"blue-ish"},{"r":125,"g":234,"b":86,"label":"green-ish"},{"r":190,"g":165,"b":123,"label":"red-ish"},{"r":90,"g":29,"b":228,"label":"blue-ish"},{"r":220,"g":61,"b":23,"label":"red-ish"},{"r":31,"g":33,"b":233,"label":"blue-ish"},{"r":101,"g":151,"b":0,"label":"green-ish"},{"r":160,"g":11,"b":50,"label":"red-ish"},{"r":130,"g":239,"b":226,"label":"green-ish"},{"r":83,"g":171,"b":172,"label":"blue-ish"},{"r":29,"g":93,"b":157,"label":"blue-ish"},{"r":26,"g":6,"b":216,"label":"blue-ish"},{"r":16,"g":82,"b":171,"label":"blue-ish"},{"r":235,"g":8,"b":160,"label":"red-ish"},{"r":73,"g":13,"b":148,"label":"blue-ish"},{"r":231,"g":5,"b":69,"label":"red-ish"},{"r":220,"g":197,"b":104,"label":"red-ish"},{"r":141,"g":32,"b":10,"label":"red-ish"},{"r":78,"g":153,"b":18,"label":"green-ish"},{"r":54,"g":7,"b":70,"label":"blue-ish"},{"r":124,"g":70,"b":16,"label":"red-ish"},{"r":108,"g":89,"b":239,"label":"blue-ish"},{"r":181,"g":16,"b":30,"label":"red-ish"},{"r":43,"g":69,"b":164,"label":"blue-ish"},{"r":98,"g":23,"b":162,"label":"blue-ish"},{"r":252,"g":90,"b":79,"label":"red-ish"},{"r":54,"g":157,"b":160,"label":"blue-ish"},{"r":55,"g":149,"b":132,"label":"green-ish"},{"r":107,"g":87,"b":178,"label":"blue-ish"},{"r":211,"g":121,"b":160,"label":"red-ish"},{"r":89,"g":172,"b":154,"label":"green-ish"},{"r":99,"g":192,"b":14,"label":"green-ish"},{"r":196,"g":43,"b":144,"label":"red-ish"},{"r":127,"g":6,"b":50,"label":"red-ish"},{"r":178,"g":213,"b":227,"label":"blue-ish"},{"r":66,"g":54,"b":96,"label":"blue-ish"},{"r":2,"g":177,"b":113,"label":"green-ish"},{"r":119,"g":120,"b":163,"label":"blue-ish"},{"r":157,"g":229,"b":153,"label":"green-ish"},{"r":108,"g":194,"b":254,"label":"blue-ish"},{"r":144,"g":240,"b":208,"label":"green-ish"},{"r":190,"g":250,"b":29,"label":"green-ish"},{"r":102,"g":211,"b":35,"label":"green-ish"},{"r":66,"g":18,"b":39,"label":"red-ish"},{"r":97,"g":131,"b":192,"label":"blue-ish"},{"r":176,"g":202,"b":233,"label":"blue-ish"},{"r":54,"g":52,"b":42,"label":"red-ish"},{"r":38,"g":65,"b":129,"label":"blue-ish"},{"r":68,"g":122,"b":7,"label":"green-ish"},{"r":226,"g":214,"b":203,"label":"red-ish"},{"r":49,"g":182,"b":217,"label":"blue-ish"},{"r":217,"g":13,"b":252,"label":"blue-ish"},{"r":13,"g":170,"b":114,"label":"green-ish"},{"r":70,"g":43,"b":44,"label":"red-ish"},{"r":251,"g":103,"b":104,"label":"red-ish"},{"r":48,"g":7,"b":250,"label":"blue-ish"},{"r":169,"g":83,"b":44,"label":"red-ish"},{"r":104,"g":59,"b":240,"label":"blue-ish"},{"r":128,"g":55,"b":163,"label":"blue-ish"},{"r":192,"g":106,"b":191,"label":"red-ish"},{"r":55,"g":253,"b":239,"label":"green-ish"},{"r":175,"g":95,"b":92,"label":"red-ish"},{"r":99,"g":93,"b":20,"label":"red-ish"},{"r":25,"g":206,"b":64,"label":"green-ish"},{"r":183,"g":32,"b":145,"label":"red-ish"},{"r":74,"g":212,"b":162,"label":"green-ish"},{"r":133,"g":77,"b":62,"label":"red-ish"},{"r":125,"g":121,"b":61,"label":"red-ish"},{"r":156,"g":136,"b":202,"label":"blue-ish"},{"r":111,"g":248,"b":144,"label":"green-ish"},{"r":113,"g":47,"b":132,"label":"blue-ish"},{"r":192,"g":254,"b":72,"label":"green-ish"},{"r":244,"g":173,"b":61,"label":"red-ish"},{"r":152,"g":79,"b":169,"label":"blue-ish"},{"r":203,"g":13,"b":40,"label":"red-ish"},{"r":56,"g":52,"b":12,"label":"red-ish"},{"r":142,"g":73,"b":208,"label":"blue-ish"},{"r":5,"g":240,"b":202,"label":"green-ish"},{"r":91,"g":23,"b":127,"label":"blue-ish"},{"r":168,"g":246,"b":45,"label":"green-ish"},{"r":129,"g":83,"b":114,"label":"red-ish"},{"r":112,"g":192,"b":30,"label":"green-ish"},{"r":54,"g":206,"b":108,"label":"green-ish"},{"r":8,"g":39,"b":150,"label":"blue-ish"},{"r":207,"g":27,"b":177,"label":"red-ish"},{"r":29,"g":162,"b":91,"label":"green-ish"},{"r":74,"g":32,"b":20,"label":"red-ish"},{"r":176,"g":228,"b":108,"label":"green-ish"},{"r":95,"g":146,"b":34,"label":"green-ish"},{"r":63,"g":254,"b":13,"label":"green-ish"},{"r":186,"g":208,"b":194,"label":"green-ish"},{"r":189,"g":190,"b":127,"label":"green-ish"},{"r":145,"g":141,"b":241,"label":"blue-ish"},{"r":134,"g":116,"b":219,"label":"blue-ish"},{"r":39,"g":163,"b":210,"label":"blue-ish"},{"r":213,"g":109,"b":151,"label":"red-ish"},{"r":202,"g":16,"b":74,"label":"red-ish"},{"r":92,"g":183,"b":45,"label":"green-ish"},{"r":140,"g":33,"b":110,"label":"red-ish"},{"r":3,"g":14,"b":240,"label":"blue-ish"},{"r":10,"g":24,"b":59,"label":"blue-ish"},{"r":0,"g":59,"b":249,"label":"blue-ish"},{"r":166,"g":42,"b":84,"label":"red-ish"},{"r":13,"g":207,"b":123,"label":"green-ish"},{"r":80,"g":110,"b":59,"label":"green-ish"},{"r":245,"g":195,"b":18,"label":"red-ish"},{"r":72,"g":189,"b":213,"label":"blue-ish"},{"r":103,"g":171,"b":199,"label":"blue-ish"},{"r":220,"g":120,"b":189,"label":"red-ish"},{"r":211,"g":195,"b":5,"label":"red-ish"},{"r":93,"g":46,"b":194,"label":"blue-ish"},{"r":9,"g":254,"b":35,"label":"green-ish"},{"r":171,"g":136,"b":233,"label":"blue-ish"},{"r":235,"g":19,"b":91,"label":"red-ish"},{"r":26,"g":213,"b":194,"label":"green-ish"},{"r":134,"g":164,"b":75,"label":"green-ish"},{"r":9,"g":226,"b":33,"label":"green-ish"},{"r":184,"g":248,"b":100,"label":"green-ish"},{"r":230,"g":224,"b":146,"label":"red-ish"},{"r":226,"g":135,"b":193,"label":"red-ish"},{"r":98,"g":248,"b":166,"label":"green-ish"},{"r":5,"g":61,"b":35,"label":"green-ish"},{"r":42,"g":249,"b":154,"label":"green-ish"},{"r":73,"g":106,"b":109,"label":"blue-ish"},{"r":29,"g":137,"b":39,"label":"green-ish"},{"r":109,"g":10,"b":77,"label":"red-ish"},{"r":214,"g":21,"b":44,"label":"red-ish"},{"r":82,"g":149,"b":212,"label":"blue-ish"},{"r":73,"g":226,"b":225,"label":"green-ish"},{"r":154,"g":160,"b":112,"label":"green-ish"},{"r":2,"g":21,"b":158,"label":"blue-ish"},{"r":101,"g":237,"b":216,"label":"green-ish"},{"r":101,"g":153,"b":105,"label":"green-ish"},{"r":34,"g":157,"b":84,"label":"green-ish"},{"r":52,"g":69,"b":178,"label":"blue-ish"},{"r":231,"g":31,"b":35,"label":"red-ish"},{"r":35,"g":36,"b":231,"label":"blue-ish"},{"r":199,"g":124,"b":106,"label":"red-ish"},{"r":133,"g":74,"b":107,"label":"red-ish"},{"r":220,"g":75,"b":28,"label":"red-ish"},{"r":90,"g":9,"b":82,"label":"red-ish"},{"r":221,"g":116,"b":59,"label":"red-ish"},{"r":253,"g":125,"b":194,"label":"red-ish"},{"r":219,"g":110,"b":121,"label":"red-ish"},{"r":35,"g":23,"b":228,"label":"blue-ish"},{"r":40,"g":83,"b":89,"label":"blue-ish"},{"r":33,"g":15,"b":160,"label":"blue-ish"},{"r":136,"g":179,"b":139,"label":"green-ish"},{"r":157,"g":129,"b":86,"label":"red-ish"},{"r":115,"g":101,"b":145,"label":"blue-ish"},{"r":209,"g":39,"b":208,"label":"red-ish"},{"r":138,"g":75,"b":74,"label":"red-ish"},{"r":43,"g":218,"b":146,"label":"green-ish"},{"r":147,"g":246,"b":77,"label":"green-ish"},{"r":121,"g":54,"b":89,"label":"red-ish"},{"r":33,"g":123,"b":25,"label":"green-ish"},{"r":139,"g":131,"b":70,"label":"red-ish"},{"r":27,"g":63,"b":212,"label":"blue-ish"},{"r":102,"g":12,"b":253,"label":"blue-ish"},{"r":130,"g":27,"b":205,"label":"blue-ish"},{"r":108,"g":168,"b":112,"label":"green-ish"},{"r":229,"g":197,"b":102,"label":"red-ish"},{"r":98,"g":35,"b":238,"label":"blue-ish"},{"r":13,"g":66,"b":83,"label":"blue-ish"},{"r":157,"g":15,"b":68,"label":"red-ish"},{"r":43,"g":149,"b":216,"label":"blue-ish"},{"r":38,"g":198,"b":16,"label":"green-ish"},{"r":188,"g":223,"b":104,"label":"green-ish"},{"r":93,"g":152,"b":193,"label":"blue-ish"},{"r":134,"g":36,"b":125,"label":"red-ish"},{"r":70,"g":97,"b":191,"label":"blue-ish"},{"r":74,"g":242,"b":152,"label":"green-ish"},{"r":120,"g":134,"b":76,"label":"green-ish"},{"r":92,"g":151,"b":160,"label":"blue-ish"},{"r":62,"g":181,"b":12,"label":"green-ish"},{"r":101,"g":232,"b":138,"label":"green-ish"},{"r":75,"g":102,"b":175,"label":"blue-ish"},{"r":154,"g":11,"b":187,"label":"blue-ish"},{"r":131,"g":113,"b":203,"label":"blue-ish"},{"r":104,"g":154,"b":122,"label":"green-ish"},{"r":114,"g":124,"b":43,"label":"green-ish"},{"r":203,"g":216,"b":246,"label":"blue-ish"},{"r":14,"g":134,"b":105,"label":"green-ish"},{"r":32,"g":107,"b":151,"label":"blue-ish"},{"r":43,"g":160,"b":217,"label":"blue-ish"},{"r":125,"g":98,"b":106,"label":"red-ish"},{"r":99,"g":123,"b":102,"label":"green-ish"},{"r":204,"g":72,"b":60,"label":"red-ish"},{"r":116,"g":231,"b":40,"label":"green-ish"},{"r":117,"g":115,"b":76,"label":"red-ish"},{"r":21,"g":85,"b":135,"label":"blue-ish"},{"r":82,"g":239,"b":190,"label":"green-ish"},{"r":173,"g":38,"b":182,"label":"blue-ish"},{"r":9,"g":26,"b":47,"label":"blue-ish"},{"r":25,"g":200,"b":141,"label":"green-ish"},{"r":34,"g":237,"b":49,"label":"green-ish"},{"r":201,"g":70,"b":176,"label":"red-ish"},{"r":73,"g":24,"b":98,"label":"blue-ish"},{"r":4,"g":244,"b":109,"label":"green-ish"},{"r":71,"g":180,"b":189,"label":"blue-ish"},{"r":188,"g":208,"b":232,"label":"blue-ish"},{"r":136,"g":218,"b":102,"label":"green-ish"},{"r":50,"g":122,"b":44,"label":"green-ish"},{"r":81,"g":85,"b":235,"label":"blue-ish"},{"r":97,"g":253,"b":15,"label":"green-ish"},{"r":22,"g":9,"b":78,"label":"blue-ish"},{"r":26,"g":219,"b":165,"label":"green-ish"},{"r":248,"g":176,"b":160,"label":"red-ish"},{"r":206,"g":167,"b":163,"label":"red-ish"},{"r":133,"g":12,"b":9,"label":"red-ish"},{"r":23,"g":242,"b":17,"label":"green-ish"},{"r":129,"g":192,"b":205,"label":"blue-ish"},{"r":252,"g":109,"b":20,"label":"red-ish"},{"r":149,"g":160,"b":9,"label":"green-ish"},{"r":176,"g":206,"b":97,"label":"green-ish"},{"r":197,"g":179,"b":157,"label":"red-ish"},{"r":22,"g":139,"b":194,"label":"blue-ish"},{"r":95,"g":148,"b":136,"label":"green-ish"},{"r":188,"g":171,"b":45,"label":"red-ish"},{"r":102,"g":64,"b":82,"label":"red-ish"},{"r":179,"g":235,"b":229,"label":"green-ish"},{"r":147,"g":69,"b":73,"label":"red-ish"},{"r":46,"g":188,"b":32,"label":"green-ish"},{"r":253,"g":107,"b":248,"label":"red-ish"},{"r":16,"g":57,"b":65,"label":"blue-ish"},{"r":36,"g":157,"b":52,"label":"green-ish"},{"r":164,"g":64,"b":32,"label":"red-ish"},{"r":95,"g":48,"b":210,"label":"blue-ish"},{"r":220,"g":113,"b":249,"label":"blue-ish"},{"r":67,"g":165,"b":33,"label":"green-ish"},{"r":22,"g":169,"b":10,"label":"green-ish"},{"r":7,"g":83,"b":82,"label":"green-ish"},{"r":231,"g":65,"b":168,"label":"red-ish"},{"r":248,"g":117,"b":90,"label":"red-ish"},{"r":95,"g":117,"b":225,"label":"blue-ish"},{"r":78,"g":136,"b":92,"label":"green-ish"},{"r":26,"g":69,"b":228,"label":"blue-ish"},{"r":83,"g":84,"b":89,"label":"blue-ish"},{"r":229,"g":35,"b":39,"label":"red-ish"},{"r":17,"g":28,"b":17,"label":"green-ish"},{"r":191,"g":38,"b":62,"label":"red-ish"},{"r":96,"g":119,"b":142,"label":"blue-ish"},{"r":160,"g":50,"b":89,"label":"red-ish"},{"r":194,"g":67,"b":106,"label":"red-ish"},{"r":91,"g":94,"b":251,"label":"blue-ish"},{"r":253,"g":254,"b":198,"label":"green-ish"},{"r":162,"g":93,"b":59,"label":"red-ish"},{"r":135,"g":180,"b":16,"label":"green-ish"},{"r":74,"g":199,"b":222,"label":"blue-ish"},{"r":156,"g":42,"b":181,"label":"blue-ish"},{"r":54,"g":171,"b":67,"label":"green-ish"},{"r":4,"g":52,"b":172,"label":"blue-ish"},{"r":177,"g":228,"b":73,"label":"green-ish"},{"r":39,"g":92,"b":186,"label":"blue-ish"},{"r":194,"g":99,"b":54,"label":"red-ish"},{"r":37,"g":139,"b":129,"label":"green-ish"},{"r":38,"g":203,"b":174,"label":"green-ish"},{"r":139,"g":167,"b":219,"label":"blue-ish"},{"r":173,"g":12,"b":112,"label":"red-ish"},{"r":125,"g":122,"b":202,"label":"blue-ish"},{"r":69,"g":57,"b":61,"label":"red-ish"},{"r":153,"g":70,"b":187,"label":"blue-ish"},{"r":91,"g":219,"b":71,"label":"green-ish"},{"r":107,"g":84,"b":140,"label":"blue-ish"},{"r":208,"g":150,"b":96,"label":"red-ish"},{"r":37,"g":67,"b":47,"label":"green-ish"},{"r":244,"g":191,"b":38,"label":"red-ish"},{"r":171,"g":41,"b":235,"label":"blue-ish"},{"r":61,"g":204,"b":10,"label":"green-ish"},{"r":22,"g":176,"b":196,"label":"blue-ish"},{"r":64,"g":8,"b":1,"label":"red-ish"},{"r":110,"g":42,"b":153,"label":"blue-ish"},{"r":242,"g":141,"b":19,"label":"red-ish"},{"r":100,"g":222,"b":212,"label":"green-ish"},{"r":122,"g":89,"b":4,"label":"red-ish"},{"r":148,"g":19,"b":187,"label":"blue-ish"},{"r":244,"g":220,"b":154,"label":"red-ish"},{"r":229,"g":13,"b":201,"label":"red-ish"},{"r":70,"g":250,"b":206,"label":"green-ish"},{"r":118,"g":202,"b":71,"label":"green-ish"},{"r":253,"g":134,"b":172,"label":"red-ish"},{"r":168,"g":151,"b":234,"label":"blue-ish"},{"r":145,"g":230,"b":253,"label":"blue-ish"},{"r":135,"g":197,"b":204,"label":"blue-ish"},{"r":77,"g":117,"b":29,"label":"green-ish"},{"r":27,"g":171,"b":132,"label":"green-ish"},{"r":125,"g":150,"b":81,"label":"green-ish"},{"r":35,"g":24,"b":186,"label":"blue-ish"},{"r":230,"g":129,"b":10,"label":"red-ish"},{"r":13,"g":239,"b":172,"label":"green-ish"},{"r":0,"g":113,"b":174,"label":"blue-ish"},{"r":191,"g":168,"b":25,"label":"red-ish"},{"r":28,"g":113,"b":189,"label":"blue-ish"},{"r":126,"g":158,"b":233,"label":"blue-ish"},{"r":251,"g":28,"b":105,"label":"red-ish"},{"r":251,"g":171,"b":174,"label":"red-ish"},{"r":23,"g":170,"b":186,"label":"blue-ish"},{"r":201,"g":226,"b":163,"label":"green-ish"},{"r":56,"g":147,"b":37,"label":"green-ish"},{"r":198,"g":142,"b":79,"label":"red-ish"},{"r":254,"g":150,"b":229,"label":"red-ish"},{"r":193,"g":87,"b":152,"label":"red-ish"},{"r":25,"g":175,"b":53,"label":"green-ish"},{"r":218,"g":107,"b":81,"label":"red-ish"},{"r":229,"g":183,"b":36,"label":"red-ish"},{"r":80,"g":107,"b":217,"label":"blue-ish"},{"r":50,"g":147,"b":198,"label":"blue-ish"},{"r":169,"g":77,"b":53,"label":"red-ish"},{"r":186,"g":99,"b":199,"label":"blue-ish"},{"r":217,"g":24,"b":10,"label":"red-ish"},{"r":218,"g":94,"b":213,"label":"red-ish"},{"r":211,"g":57,"b":43,"label":"red-ish"},{"r":224,"g":129,"b":223,"label":"red-ish"},{"r":66,"g":186,"b":46,"label":"green-ish"},{"r":163,"g":149,"b":97,"label":"red-ish"},{"r":65,"g":5,"b":218,"label":"blue-ish"},{"r":18,"g":13,"b":72,"label":"blue-ish"},{"r":0,"g":54,"b":140,"label":"blue-ish"},{"r":73,"g":249,"b":136,"label":"green-ish"},{"r":210,"g":21,"b":74,"label":"red-ish"},{"r":200,"g":108,"b":111,"label":"red-ish"},{"r":189,"g":250,"b":88,"label":"green-ish"},{"r":49,"g":180,"b":198,"label":"blue-ish"},{"r":4,"g":84,"b":172,"label":"blue-ish"},{"r":199,"g":252,"b":241,"label":"green-ish"},{"r":45,"g":220,"b":72,"label":"green-ish"},{"r":63,"g":139,"b":27,"label":"green-ish"},{"r":8,"g":4,"b":75,"label":"blue-ish"},{"r":62,"g":27,"b":126,"label":"blue-ish"},{"r":122,"g":191,"b":6,"label":"green-ish"},{"r":76,"g":104,"b":150,"label":"blue-ish"},{"r":140,"g":40,"b":63,"label":"red-ish"},{"r":27,"g":51,"b":235,"label":"blue-ish"},{"r":17,"g":166,"b":192,"label":"blue-ish"},{"r":4,"g":211,"b":60,"label":"green-ish"},{"r":162,"g":53,"b":75,"label":"red-ish"},{"r":59,"g":61,"b":200,"label":"blue-ish"},{"r":170,"g":36,"b":214,"label":"blue-ish"},{"r":159,"g":142,"b":38,"label":"red-ish"},{"r":205,"g":226,"b":159,"label":"green-ish"},{"r":239,"g":114,"b":1,"label":"red-ish"},{"r":121,"g":173,"b":18,"label":"green-ish"},{"r":48,"g":175,"b":78,"label":"green-ish"},{"r":210,"g":122,"b":173,"label":"red-ish"},{"r":245,"g":167,"b":70,"label":"red-ish"},{"r":141,"g":113,"b":177,"label":"blue-ish"},{"r":168,"g":35,"b":192,"label":"blue-ish"},{"r":162,"g":98,"b":121,"label":"red-ish"},{"r":112,"g":225,"b":82,"label":"green-ish"},{"r":75,"g":40,"b":75,"label":"red-ish"},{"r":236,"g":180,"b":97,"label":"red-ish"},{"r":170,"g":47,"b":142,"label":"red-ish"},{"r":94,"g":72,"b":164,"label":"blue-ish"},{"r":67,"g":246,"b":34,"label":"green-ish"},{"r":105,"g":161,"b":176,"label":"blue-ish"},{"r":126,"g":64,"b":240,"label":"blue-ish"},{"r":166,"g":126,"b":246,"label":"blue-ish"},{"r":48,"g":116,"b":100,"label":"green-ish"},{"r":98,"g":47,"b":89,"label":"red-ish"},{"r":14,"g":238,"b":82,"label":"green-ish"},{"r":82,"g":3,"b":118,"label":"blue-ish"},{"r":207,"g":206,"b":131,"label":"red-ish"},{"r":107,"g":93,"b":104,"label":"red-ish"},{"r":232,"g":79,"b":162,"label":"red-ish"},{"r":71,"g":24,"b":95,"label":"blue-ish"},{"r":209,"g":76,"b":131,"label":"red-ish"},{"r":1,"g":162,"b":159,"label":"green-ish"},{"r":192,"g":93,"b":168,"label":"red-ish"},{"r":110,"g":8,"b":227,"label":"blue-ish"},{"r":75,"g":219,"b":44,"label":"green-ish"},{"r":85,"g":156,"b":151,"label":"green-ish"},{"r":108,"g":166,"b":68,"label":"green-ish"},{"r":130,"g":16,"b":143,"label":"blue-ish"},{"r":33,"g":41,"b":152,"label":"blue-ish"},{"r":232,"g":208,"b":34,"label":"red-ish"},{"r":2,"g":250,"b":92,"label":"green-ish"},{"r":147,"g":179,"b":227,"label":"blue-ish"},{"r":27,"g":25,"b":143,"label":"blue-ish"},{"r":219,"g":69,"b":114,"label":"red-ish"},{"r":74,"g":76,"b":73,"label":"green-ish"},{"r":203,"g":34,"b":59,"label":"red-ish"},{"r":145,"g":16,"b":235,"label":"blue-ish"},{"r":162,"g":110,"b":5,"label":"red-ish"},{"r":173,"g":201,"b":10,"label":"green-ish"},{"r":192,"g":217,"b":13,"label":"green-ish"},{"r":130,"g":62,"b":83,"label":"red-ish"},{"r":128,"g":75,"b":97,"label":"red-ish"},{"r":31,"g":73,"b":21,"label":"green-ish"},{"r":145,"g":183,"b":53,"label":"green-ish"},{"r":241,"g":21,"b":26,"label":"red-ish"},{"r":31,"g":161,"b":29,"label":"green-ish"},{"r":53,"g":27,"b":107,"label":"blue-ish"},{"r":74,"g":107,"b":51,"label":"green-ish"},{"r":222,"g":43,"b":199,"label":"red-ish"},{"r":74,"g":37,"b":127,"label":"blue-ish"},{"r":30,"g":7,"b":148,"label":"blue-ish"},{"r":55,"g":244,"b":183,"label":"green-ish"},{"r":176,"g":51,"b":93,"label":"red-ish"},{"r":243,"g":93,"b":109,"label":"red-ish"},{"r":87,"g":106,"b":83,"label":"green-ish"},{"r":34,"g":129,"b":237,"label":"blue-ish"},{"r":104,"g":117,"b":141,"label":"blue-ish"},{"r":163,"g":215,"b":198,"label":"green-ish"},{"r":105,"g":136,"b":213,"label":"blue-ish"},{"r":26,"g":212,"b":53,"label":"green-ish"},{"r":184,"g":31,"b":102,"label":"red-ish"},{"r":135,"g":45,"b":99,"label":"red-ish"},{"r":105,"g":135,"b":253,"label":"blue-ish"},{"r":0,"g":174,"b":29,"label":"green-ish"},{"r":180,"g":223,"b":26,"label":"green-ish"},{"r":39,"g":113,"b":171,"label":"blue-ish"},{"r":21,"g":97,"b":127,"label":"blue-ish"},{"r":142,"g":226,"b":63,"label":"green-ish"},{"r":132,"g":230,"b":10,"label":"green-ish"},{"r":117,"g":240,"b":109,"label":"green-ish"},{"r":19,"g":5,"b":64,"label":"blue-ish"},{"r":250,"g":42,"b":138,"label":"red-ish"},{"r":148,"g":107,"b":173,"label":"blue-ish"},{"r":50,"g":97,"b":68,"label":"green-ish"},{"r":7,"g":74,"b":172,"label":"blue-ish"},{"r":217,"g":156,"b":15,"label":"red-ish"},{"r":106,"g":58,"b":142,"label":"blue-ish"},{"r":106,"g":247,"b":113,"label":"green-ish"},{"r":239,"g":191,"b":206,"label":"red-ish"},{"r":6,"g":38,"b":191,"label":"blue-ish"},{"r":132,"g":80,"b":222,"label":"blue-ish"},{"r":50,"g":230,"b":52,"label":"green-ish"},{"r":0,"g":252,"b":246,"label":"green-ish"},{"r":120,"g":245,"b":127,"label":"green-ish"},{"r":106,"g":149,"b":177,"label":"blue-ish"},{"r":171,"g":188,"b":30,"label":"green-ish"},{"r":191,"g":225,"b":22,"label":"green-ish"},{"r":210,"g":16,"b":162,"label":"red-ish"},{"r":195,"g":97,"b":26,"label":"red-ish"},{"r":216,"g":81,"b":150,"label":"red-ish"},{"r":146,"g":230,"b":99,"label":"green-ish"},{"r":210,"g":23,"b":250,"label":"blue-ish"},{"r":125,"g":115,"b":110,"label":"red-ish"},{"r":120,"g":22,"b":17,"label":"red-ish"},{"r":108,"g":123,"b":139,"label":"blue-ish"},{"r":207,"g":125,"b":31,"label":"red-ish"},{"r":190,"g":248,"b":12,"label":"green-ish"},{"r":199,"g":238,"b":227,"label":"green-ish"},{"r":224,"g":75,"b":56,"label":"red-ish"},{"r":71,"g":198,"b":187,"label":"green-ish"},{"r":92,"g":123,"b":160,"label":"blue-ish"},{"r":233,"g":105,"b":105,"label":"red-ish"},{"r":237,"g":123,"b":170,"label":"red-ish"},{"r":132,"g":50,"b":68,"label":"red-ish"},{"r":7,"g":130,"b":157,"label":"blue-ish"},{"r":167,"g":135,"b":239,"label":"blue-ish"},{"r":40,"g":130,"b":122,"label":"green-ish"},{"r":27,"g":42,"b":112,"label":"blue-ish"},{"r":191,"g":185,"b":100,"label":"red-ish"},{"r":51,"g":233,"b":65,"label":"green-ish"},{"r":170,"g":225,"b":66,"label":"green-ish"},{"r":15,"g":172,"b":221,"label":"blue-ish"},{"r":123,"g":16,"b":54,"label":"red-ish"},{"r":25,"g":175,"b":227,"label":"blue-ish"},{"r":170,"g":169,"b":162,"label":"red-ish"},{"r":66,"g":45,"b":248,"label":"blue-ish"},{"r":161,"g":115,"b":193,"label":"blue-ish"},{"r":169,"g":43,"b":162,"label":"red-ish"},{"r":154,"g":121,"b":205,"label":"blue-ish"},{"r":103,"g":213,"b":76,"label":"green-ish"},{"r":167,"g":244,"b":56,"label":"green-ish"},{"r":201,"g":193,"b":236,"label":"blue-ish"},{"r":71,"g":134,"b":21,"label":"green-ish"},{"r":25,"g":10,"b":76,"label":"blue-ish"},{"r":130,"g":178,"b":168,"label":"green-ish"},{"r":123,"g":249,"b":71,"label":"green-ish"},{"r":183,"g":5,"b":165,"label":"red-ish"},{"r":86,"g":125,"b":103,"label":"green-ish"},{"r":174,"g":218,"b":207,"label":"green-ish"},{"r":94,"g":131,"b":54,"label":"green-ish"},{"r":190,"g":61,"b":196,"label":"blue-ish"},{"r":151,"g":39,"b":232,"label":"blue-ish"},{"r":7,"g":114,"b":175,"label":"blue-ish"},{"r":229,"g":29,"b":207,"label":"red-ish"},{"r":79,"g":75,"b":156,"label":"blue-ish"},{"r":248,"g":70,"b":14,"label":"red-ish"},{"r":64,"g":86,"b":142,"label":"blue-ish"},{"r":1,"g":39,"b":107,"label":"blue-ish"},{"r":101,"g":223,"b":133,"label":"green-ish"},{"r":85,"g":157,"b":109,"label":"green-ish"},{"r":164,"g":226,"b":127,"label":"green-ish"},{"r":218,"g":72,"b":47,"label":"red-ish"},{"r":76,"g":26,"b":163,"label":"blue-ish"},{"r":203,"g":128,"b":226,"label":"blue-ish"},{"r":220,"g":50,"b":252,"label":"blue-ish"},{"r":133,"g":150,"b":205,"label":"blue-ish"},{"r":58,"g":104,"b":63,"label":"green-ish"},{"r":124,"g":118,"b":194,"label":"blue-ish"},{"r":168,"g":33,"b":119,"label":"red-ish"},{"r":152,"g":188,"b":114,"label":"green-ish"},{"r":107,"g":122,"b":152,"label":"blue-ish"},{"r":231,"g":175,"b":127,"label":"red-ish"},{"r":228,"g":216,"b":151,"label":"red-ish"},{"r":248,"g":11,"b":23,"label":"red-ish"},{"r":69,"g":129,"b":136,"label":"blue-ish"},{"r":145,"g":56,"b":51,"label":"red-ish"},{"r":253,"g":241,"b":54,"label":"red-ish"},{"r":240,"g":222,"b":222,"label":"red-ish"},{"r":12,"g":179,"b":175,"label":"green-ish"},{"r":215,"g":128,"b":26,"label":"red-ish"},{"r":167,"g":153,"b":214,"label":"blue-ish"},{"r":93,"g":67,"b":149,"label":"blue-ish"},{"r":76,"g":87,"b":42,"label":"green-ish"},{"r":85,"g":159,"b":108,"label":"green-ish"},{"r":170,"g":212,"b":247,"label":"blue-ish"},{"r":128,"g":166,"b":79,"label":"green-ish"},{"r":14,"g":180,"b":42,"label":"green-ish"},{"r":177,"g":215,"b":197,"label":"green-ish"},{"r":116,"g":73,"b":226,"label":"blue-ish"},{"r":237,"g":245,"b":185,"label":"green-ish"},{"r":7,"g":97,"b":6,"label":"green-ish"},{"r":167,"g":243,"b":36,"label":"green-ish"},{"r":141,"g":28,"b":90,"label":"red-ish"},{"r":96,"g":214,"b":127,"label":"green-ish"},{"r":15,"g":65,"b":177,"label":"blue-ish"},{"r":58,"g":33,"b":158,"label":"blue-ish"},{"r":178,"g":80,"b":125,"label":"red-ish"},{"r":72,"g":100,"b":162,"label":"blue-ish"},{"r":39,"g":187,"b":215,"label":"blue-ish"},{"r":72,"g":230,"b":87,"label":"green-ish"},{"r":193,"g":88,"b":161,"label":"red-ish"},{"r":141,"g":100,"b":241,"label":"blue-ish"},{"r":118,"g":243,"b":155,"label":"green-ish"},{"r":160,"g":229,"b":171,"label":"green-ish"},{"r":195,"g":84,"b":37,"label":"red-ish"},{"r":78,"g":82,"b":32,"label":"green-ish"},{"r":174,"g":3,"b":24,"label":"red-ish"}]